nixio/__init__.py
nixio/block.py
nixio/compression.py
nixio/container.py
nixio/data_array.py
nixio/data_frame.py
nixio/data_set.py
nixio/data_view.py
nixio/datatype.py
nixio/dimension_type.py
nixio/dimensions.py
nixio/entity.py
nixio/feature.py
nixio/file.py
nixio/group.py
nixio/info.json
nixio/info.py
nixio/link_type.py
nixio/multi_tag.py
nixio/property.py
nixio/section.py
nixio/source.py
nixio/source_link_container.py
nixio/tag.py
nixio/validator.py
nixio/cmd/__init__.py
nixio/cmd/explore.py
nixio/cmd/main.py
nixio/cmd/upgrade.py
nixio/cmd/validate.py
nixio/exceptions/__init__.py
nixio/exceptions/exceptions.py
nixio/hdf5/__init__.py
nixio/hdf5/h5dataset.py
nixio/hdf5/h5group.py
nixio/util/__init__.py
nixio/util/find.py
nixio/util/names.py
nixio/util/units.py
nixio/util/util.py
nixio-1.5.3.dist-info/LICENSE
nixio-1.5.3.dist-info/METADATA
nixio-1.5.3.dist-info/WHEEL
nixio-1.5.3.dist-info/entry_points.txt
nixio-1.5.3.dist-info/top_level.txt
nixio-1.5.3.dist-info/RECORD
