Metadata-Version: 2.1
Name: nixio
Version: 1.5.3
Summary: Python reimplementation of NIXIO (http://g-node.github.io/nix/)
Home-page: https://github.com/G-Node/nixpy
Author: Christian Kellner, Adrian Stoewer, Andrey Sobolev, Jan Grewe, Balint Morvai, Achilleas Koutsou
Author-email: dev@g-node.org
License: BSD
Platform: UNKNOWN
Classifier: Development Status :: 5 - Production/Stable
Classifier: Programming Language :: Python
Classifier: Programming Language :: Python :: 3.6
Classifier: Programming Language :: Python :: 3.7
Classifier: Topic :: Scientific/Engineering
Requires-Python: >=3.6
License-File: LICENSE
Requires-Dist: numpy
Requires-Dist: h5py
Requires-Dist: six
Requires-Dist: enum34 ; python_version < "3.4"
